brutalmaze/__init__.py
brutalmaze/__main__.py
brutalmaze/characters.py
brutalmaze/constants.py
brutalmaze/icon.png
brutalmaze/maze.py
brutalmaze/misc.py
brutalmaze/settings.ini
brutalmaze/weapons.py
brutalmaze/soundfx/__init__.py
brutalmaze/soundfx/heart.ogg
brutalmaze/soundfx/lose.ogg
brutalmaze/soundfx/missed.ogg
brutalmaze/soundfx/noise.ogg
brutalmaze/soundfx/shot-enemy.ogg
brutalmaze/soundfx/shot-hero.ogg
brutalmaze/soundfx/slash-enemy.ogg
brutalmaze/soundfx/slash-hero.ogg
brutalmaze/soundfx/spawn.ogg
brutalmaze-1.1.1.dist-info/entry_points.txt
brutalmaze-1.1.1.dist-info/LICENSE
brutalmaze-1.1.1.dist-info/WHEEL
brutalmaze-1.1.1.dist-info/METADATA
brutalmaze-1.1.1.dist-info/RECORD
