Metadata-Version: 2.1
Name: brutalmaze
Version: 1.1.1
Summary: Minimalist thrilling shoot 'em up game
Home-page: https://sr.ht/~cnx/brutalmaze
License: AGPLv3+
Keywords: pygame,shmup,maze,ai-challenges
Author: Nguyễn Gia Phong
Author-email: mcsinyx@disroot.org
Requires-Python: >=3.7
Classifier: Development Status :: 5 - Production/Stable
Classifier: Environment :: MacOS X
Classifier: Environment :: Win32 (MS Windows)
Classifier: Environment :: X11 Applications
Classifier: Intended Audience :: End Users/Desktop
Classifier: License :: OSI Approved :: GNU Affero General Public License v3 or later (AGPLv3+)
Classifier: Natural Language :: English
Classifier: Operating System :: OS Independent
Classifier: Programming Language :: Python
Classifier: Programming Language :: Python :: 3 :: Only
Classifier: Topic :: Games/Entertainment :: Arcade
Requires-Dist: loca
Requires-Dist: palace
Requires-Dist: pygame>=2
Project-URL: Documentation, https://brutalmaze.rtfd.io
